TerraformToAnsibleInventory/__init__.py
TerraformToAnsibleInventory/_version.py
TerraformToAnsibleInventory/args.py
TerraformToAnsibleInventory/build_inventory.py
TerraformToAnsibleInventory/generate_inventory.py
TerraformToAnsibleInventory/logging_config.py
TerraformToAnsibleInventory/parse.py
TerraformToAnsibleInventory/backends/__init__.py
TerraformToAnsibleInventory/backends/consul_backend.py
TerraformToAnsibleInventory/backends/local_backend.py
TerraformToAnsibleInventory/parsers/__init__.py
TerraformToAnsibleInventory/parsers/aws_elb.py
TerraformToAnsibleInventory/parsers/aws_instance.py
TerraformToAnsibleInventory/parsers/aws_security_group.py
TerraformToAnsibleInventory/parsers/azurerm_lb.py
TerraformToAnsibleInventory/parsers/azurerm_network_interface.py
TerraformToAnsibleInventory/parsers/azurerm_network_security_group.py
TerraformToAnsibleInventory/parsers/azurerm_public_ip.py
TerraformToAnsibleInventory/parsers/azurerm_virtual_machine.py
TerraformToAnsibleInventory/parsers/vsphere_virtual_machine.py
TerraformToAnsibleInventory-0.4.0.data/scripts/TerraformToAnsibleInventory
TerraformToAnsibleInventory-0.4.0.dist-info/METADATA
TerraformToAnsibleInventory-0.4.0.dist-info/RECORD
TerraformToAnsibleInventory-0.4.0.dist-info/WHEEL
TerraformToAnsibleInventory-0.4.0.dist-info/top_level.txt
