Metadata-Version: 2.1
Name: TerraformToAnsibleInventory
Version: 0.4.0
Summary: Consumes Terraform State and generates Ansible inventory.
Home-page: https://github.com/mrlesmithjr/python-terraform-to-ansible-inventory
Author: Larry Smith Jr.
Author-email: mrlesmithjr@gmail.com
License: MIT
Platform: UNKNOWN
Classifier: Programming Language :: Python :: 2
Classifier: License :: OSI Approved :: MIT License
Classifier: Operating System :: OS Independent
Requires-Dist: argparse
Requires-Dist: ast
Requires-Dist: python-consul
Requires-Dist: jinja2
Requires-Dist: PyYaml
